uplift_ble/__init__.py
uplift_ble/ble_helpers.py
uplift_ble/ble_protos.py
uplift_ble/byte_maps.py
uplift_ble/desk_configs.py
uplift_ble/desk_controller.py
uplift_ble/desk_enums.py
uplift_ble/desk_finder.py
uplift_ble/desk_scanner.py
uplift_ble/desk_validator.py
uplift_ble/models.py
uplift_ble/packet.py
uplift_ble/utils.py
uplift_ble-0.5.1.dist-info/licenses/LICENSE
uplift_ble-0.5.1.dist-info/WHEEL
uplift_ble-0.5.1.dist-info/entry_points.txt
uplift_ble-0.5.1.dist-info/METADATA
uplift_ble-0.5.1.dist-info/RECORD
