Metadata-Version: 2.4
Name: uplift-ble
Version: 0.5.1
Summary: Python library for controlling Uplift standing desks over Bluetooth Low Energy via the official Uplift BLE adapter
Author: Eric McDonald
Author-email: Eric McDonald <106356608+librick@users.noreply.github.com>
License-Expression: MIT
License-File: LICENSE
Classifier: Development Status :: 3 - Alpha
Classifier: Framework :: AsyncIO
Classifier: Programming Language :: Python :: 3
Classifier: Operating System :: Microsoft :: Windows :: Windows 10
Classifier: Operating System :: POSIX :: Linux
Classifier: Operating System :: MacOS :: MacOS X
Requires-Dist: bleak>=1.0.1
Requires-Python: >=3.11
Project-URL: Homepage, https://github.com/librick/uplift-ble
Project-URL: Issues, https://github.com/librick/uplift-ble/issues
